reportengine/__init__.py
reportengine/api.py
reportengine/app.py
reportengine/baseexceptions.py
reportengine/checks.py
reportengine/colors.py
reportengine/configparser.py
reportengine/dag.py
reportengine/environment.py
reportengine/figure.py
reportengine/filefinder.py
reportengine/floatformatting.py
reportengine/formattingtools.py
reportengine/helputils.py
reportengine/namespaces.py
reportengine/report.py
reportengine/resourcebuilder.py
reportengine/table.py
reportengine/targets.py
reportengine/templateparser.py
reportengine/utils.py
reportengine/styles/__init__.py
reportengine/styles/report.css
reportengine/styles/report.template
reportengine/templates/__init__.py
reportengine/templates/test.md
reportengine/templates/test_new.md
reportengine/templates/test_second.md
reportengine/tests/__init__.py
reportengine/tests/_test_temparser.py
reportengine/tests/test_api.py
reportengine/tests/test_app.py
reportengine/tests/test_builder.py
reportengine/tests/test_complexinput.py
reportengine/tests/test_configparser.py
reportengine/tests/test_dag.py
reportengine/tests/test_defaults.py
reportengine/tests/test_executor.py
reportengine/tests/test_filefinder.py
reportengine/tests/test_floatformatting.py
reportengine/tests/test_formatting.py
reportengine/tests/test_helputils.py
reportengine/tests/test_namespaces.py
reportengine/tests/test_report.py
reportengine/tests/test_utils.py
reportengine/tests/utils.py
reportengine/tests/.hypothesis/examples/02999d71cd173923/7210af19145ec2a8
reportengine/tests/.hypothesis/examples/1ffa82e473737277/d3f3bcbd2c34c7fa
reportengine/tests/.hypothesis/examples/4003b369479fc18e/af10ab1a2d1d6cf6
reportengine/tests/.hypothesis/examples/6cbc8767b0f00552/47fb76aa9ccc5e34
reportengine/tests/.hypothesis/examples/e091412c3d13bb73/705ef95420cc18dd
reportengine/tests/.hypothesis/unicode_data/13.0.0/charmap.json.gz
reportengine/tests/.hypothesis/unicode_data/13.0.0/codec-utf-8.json.gz
reportengine/tests/.hypothesis/unicode_data/15.0.0/charmap.json.gz
reportengine-0.32.dist-info/WHEEL
reportengine-0.32.dist-info/METADATA
reportengine-0.32.dist-info/RECORD
