Metadata-Version: 2.3
Name: reportengine
Version: 0.32
Summary: Reportengine: A framework to organize data pypelines.
Home-page: https://github.com/NNPDF/reportengine/
Author: Zahari Kassabov
Author-email: zk261@cam.ac.uk
Classifier: License :: OSI Approved :: BSD License
Classifier: Operating System :: OS Independent
Classifier: Programming Language :: Python
Classifier: Topic :: Scientific/Engineering
Classifier: Topic :: Scientific/Engineering :: Physics
Classifier: Programming Language :: Python :: 3
Classifier: Programming Language :: Python :: 3.7
Requires-Dist: jinja2
Requires-Dist: ruamel.yaml>=0.15
Requires-Dist: matplotlib
Requires-Dist: pandas
Requires-Dist: pygments
Requires-Dist: blessings
Requires-Dist: dask[distributed]
Requires-Dist: bokeh!=3.0.*,>=2.4.2 ; extra == "dashboard"
Requires-Dist: pytest ; extra == "test"
Requires-Dist: hypothesis ; extra == "test"
Provides-Extra: dashboard
Provides-Extra: test
